amqp-stubs/__init__.pyi
amqp-stubs/exceptions.pyi
billiard-stubs/__init__.pyi
billiard-stubs/einfo.pyi
billiard-stubs/exceptions.pyi
celery-stubs/__init__.pyi
celery-stubs/_state.pyi
celery-stubs/app/__init__.pyi
celery-stubs/app/amqp.pyi
celery-stubs/app/base.pyi
celery-stubs/app/beat.pyi
celery-stubs/app/control.pyi
celery-stubs/app/events.pyi
celery-stubs/app/log.pyi
celery-stubs/app/registry.pyi
celery-stubs/app/routes.pyi
celery-stubs/app/task.pyi
celery-stubs/app/utils.pyi
celery-stubs/apps/__init__.pyi
celery-stubs/apps/worker.pyi
celery-stubs/backends/__init__.pyi
celery-stubs/backends/base.pyi
celery-stubs/bootsteps.pyi
celery-stubs/canvas.pyi
celery-stubs/concurrency/__init__.pyi
celery-stubs/concurrency/base.pyi
celery-stubs/exceptions.pyi
celery-stubs/loaders/__init__.pyi
celery-stubs/loaders/base.pyi
celery-stubs/local.pyi
celery-stubs/result.pyi
celery-stubs/schedules.pyi
celery-stubs/signals.pyi
celery-stubs/states.pyi
celery-stubs/utils/__init__.pyi
celery-stubs/utils/abstract.pyi
celery-stubs/utils/collections.pyi
celery-stubs/utils/dispatch/__init__.pyi
celery-stubs/utils/dispatch/signal.pyi
celery-stubs/utils/graph.pyi
celery-stubs/utils/log.pyi
celery-stubs/utils/objects.pyi
celery-stubs/utils/term.pyi
celery-stubs/utils/threads.pyi
celery-stubs/utils/time.pyi
celery-stubs/worker/__init__.pyi
celery-stubs/worker/autoscale.pyi
celery-stubs/worker/request.pyi
celery-stubs/worker/worker.pyi
django_celery_results-stubs/__init__.pyi
django_celery_results-stubs/managers.pyi
django_celery_results-stubs/models.pyi
ephem-stubs/__init__.pyi
kombu-stubs/__init__.pyi
kombu-stubs/abstract.pyi
kombu-stubs/connection.pyi
kombu-stubs/entity.pyi
kombu-stubs/exceptions.pyi
kombu-stubs/message.pyi
kombu-stubs/messaging.pyi
kombu-stubs/mixins.pyi
kombu-stubs/pidbox.pyi
kombu-stubs/pools.pyi
kombu-stubs/resource.pyi
kombu-stubs/serialization.pyi
kombu-stubs/transport/__init__.pyi
kombu-stubs/transport/base.pyi
kombu-stubs/utils/__init__.pyi
celery_types-0.22.0.dist-info/LICENSE
celery_types-0.22.0.dist-info/METADATA
celery_types-0.22.0.dist-info/WHEEL
celery_types-0.22.0.dist-info/RECORD
