Metadata-Version: 2.1
Name: celery-types
Version: 0.22.0
Summary: Type stubs for Celery and its related packages
Home-page: https://github.com/sbdchd/celery-types
Keywords: celery,kombu,vine,amqp,billiard,django_celery_results,types,mypy,stubs
Author: Steve Dignam
Author-email: steve@dignam.xyz
Requires-Python: >=3.9,<4.0
Classifier: Programming Language :: Python :: 3
Classifier: Programming Language :: Python :: 3.9
Classifier: Programming Language :: Python :: 3.10
Classifier: Programming Language :: Python :: 3.11
Classifier: Programming Language :: Python :: 3.12
Requires-Dist: typing-extensions (>=4.9.0,<5.0.0)
Project-URL: Repository, https://github.com/sbdchd/celery-types
